odoo/addons/stock_buffer_sales_analysis/README.rst
odoo/addons/stock_buffer_sales_analysis/__init__.py
odoo/addons/stock_buffer_sales_analysis/__manifest__.py
odoo/addons/stock_buffer_sales_analysis/i18n/es.po
odoo/addons/stock_buffer_sales_analysis/i18n/it.po
odoo/addons/stock_buffer_sales_analysis/i18n/pt_BR.po
odoo/addons/stock_buffer_sales_analysis/i18n/stock_buffer_sales_analysis.pot
odoo/addons/stock_buffer_sales_analysis/models/__init__.py
odoo/addons/stock_buffer_sales_analysis/models/stock_buffer.py
odoo/addons/stock_buffer_sales_analysis/readme/CONTRIBUTORS.rst
odoo/addons/stock_buffer_sales_analysis/readme/CREDITS.rst
odoo/addons/stock_buffer_sales_analysis/readme/DESCRIPTION.rst
odoo/addons/stock_buffer_sales_analysis/static/description/icon.png
odoo/addons/stock_buffer_sales_analysis/static/description/index.html
odoo/addons/stock_buffer_sales_analysis/views/stock_buffer_views.xml
odoo14_addon_stock_buffer_sales_analysis-14.0.1.0.1.dev8.dist-info/METADATA
odoo14_addon_stock_buffer_sales_analysis-14.0.1.0.1.dev8.dist-info/WHEEL
odoo14_addon_stock_buffer_sales_analysis-14.0.1.0.1.dev8.dist-info/top_level.txt
odoo14_addon_stock_buffer_sales_analysis-14.0.1.0.1.dev8.dist-info/RECORD
